LeetbookLeetcodeXiangjie/README.md
LeetbookLeetcodeXiangjie/__init__.py
LeetbookLeetcodeXiangjie/__main__.py
LeetbookLeetcodeXiangjie/file.epub
LeetbookLeetcodeXiangjie/index.html
LeetbookLeetcodeXiangjie/css/__init__.py
LeetbookLeetcodeXiangjie/css/annotations.css
LeetbookLeetcodeXiangjie/css/main.css
LeetbookLeetcodeXiangjie/css/normalize.css
LeetbookLeetcodeXiangjie/css/popup.css
LeetbookLeetcodeXiangjie/font/__init__.py
LeetbookLeetcodeXiangjie/font/fontello.eot
LeetbookLeetcodeXiangjie/font/fontello.svg
LeetbookLeetcodeXiangjie/font/fontello.ttf
LeetbookLeetcodeXiangjie/font/fontello.woff
LeetbookLeetcodeXiangjie/img/__init__.py
LeetbookLeetcodeXiangjie/img/annotator-glyph-sprite.png
LeetbookLeetcodeXiangjie/img/annotator-icon-sprite.png
LeetbookLeetcodeXiangjie/img/apple-touch-icon.png
LeetbookLeetcodeXiangjie/img/cancelfullscreen.png
LeetbookLeetcodeXiangjie/img/close.png
LeetbookLeetcodeXiangjie/img/fullscreen.png
LeetbookLeetcodeXiangjie/img/loader.gif
LeetbookLeetcodeXiangjie/img/menu-icon.png
LeetbookLeetcodeXiangjie/img/save.png
LeetbookLeetcodeXiangjie/img/saved.png
LeetbookLeetcodeXiangjie/img/settings-s.png
LeetbookLeetcodeXiangjie/img/settings.png
LeetbookLeetcodeXiangjie/img/star.png
LeetbookLeetcodeXiangjie/js/__init__.py
LeetbookLeetcodeXiangjie/js/epub.js
LeetbookLeetcodeXiangjie/js/epub.min.js
LeetbookLeetcodeXiangjie/js/epub.min.map
LeetbookLeetcodeXiangjie/js/hooks.min.js
LeetbookLeetcodeXiangjie/js/hooks.min.map
LeetbookLeetcodeXiangjie/js/reader.js
LeetbookLeetcodeXiangjie/js/reader.js.map
LeetbookLeetcodeXiangjie/js/reader.min.js
LeetbookLeetcodeXiangjie/js/reader.min.map
LeetbookLeetcodeXiangjie/js/hooks/__init__.py
LeetbookLeetcodeXiangjie/js/hooks/extensions/__init__.py
LeetbookLeetcodeXiangjie/js/hooks/extensions/highlight.js
LeetbookLeetcodeXiangjie/js/libs/__init__.py
LeetbookLeetcodeXiangjie/js/libs/jquery.min.js
LeetbookLeetcodeXiangjie/js/libs/localforage.min.js
LeetbookLeetcodeXiangjie/js/libs/screenfull.js
leetbook_leetcode_xiangjie-2024.3.3.0.dist-info/METADATA
leetbook_leetcode_xiangjie-2024.3.3.0.dist-info/WHEEL
leetbook_leetcode_xiangjie-2024.3.3.0.dist-info/entry_points.txt
leetbook_leetcode_xiangjie-2024.3.3.0.dist-info/top_level.txt
leetbook_leetcode_xiangjie-2024.3.3.0.dist-info/RECORD
